dsci_utils/__init__.py
dsci_utils/dsci_utils.py
dsci_utils-0.0.15.dist-info/LICENSE
dsci_utils-0.0.15.dist-info/METADATA
dsci_utils-0.0.15.dist-info/WHEEL
dsci_utils-0.0.15.dist-info/top_level.txt
dsci_utils-0.0.15.dist-info/RECORD
