Metadata-Version: 2.1
Name: dsci-utils
Version: 0.0.15
Summary: A simple toolkit to assist with data science projects
Home-page: https://github.com/ktechboston/db_utils
Author: Komodo Technologies, LLC
Author-email: joe@ktechboston.com
License: UNKNOWN
Platform: UNKNOWN
Classifier: Programming Language :: Python :: 3
Classifier: License :: OSI Approved :: MIT License
Classifier: Operating System :: OS Independent
Requires-Dist: ujson
Requires-Dist: beautifulsoup4
Requires-Dist: numpy
